taiga_contrib_gogs
