Metadata-Version: 1.1
Name: taiga-contrib-gogs
Version: 1.10
Summary: The Taiga plugin for gogs integration
Home-page: https://github.com/taigaio/taiga-contrib-gogs
Author: Jesús Espino García
Author-email: jesus.espino@kaleidos.net
License: AGPL
Keywords: taiga,gogs,integration
Platform: UNKNOWN
Classifier: Programming Language :: Python
Classifier: Development Status :: 4 - Beta
Classifier: Framework :: Django
Classifier: Intended Audience :: Developers
Classifier: License :: OSI Approved :: GNU Affero General Public License v3
Classifier: Operating System :: OS Independent
Classifier: Programming Language :: Python
Classifier: Topic :: Internet :: WWW/HTTP
